numberpartitioning/__init__.py
numberpartitioning/common.py
numberpartitioning/complete_karmarkar_karp.py
numberpartitioning/greedy.py
numberpartitioning/karmarkar_karp.py
numberpartitioning-0.0.2.dist-info/LICENSE
numberpartitioning-0.0.2.dist-info/METADATA
numberpartitioning-0.0.2.dist-info/WHEEL
numberpartitioning-0.0.2.dist-info/top_level.txt
numberpartitioning-0.0.2.dist-info/RECORD
