Metadata-Version: 2.1
Name: numberpartitioning
Version: 0.0.2
Summary: Pure Python solver for the multi-way partition problem
Home-page: https://github.com/fuglede/numberpartitioning
Author: Søren Fuglede Jørgensen
Author-email: pypi@fuglede.dk
License: UNKNOWN
Platform: UNKNOWN
Classifier: License :: OSI Approved :: MIT License
Classifier: Programming Language :: Python :: 3
Classifier: Programming Language :: Python :: 3 :: Only
Classifier: Programming Language :: Python :: 3.7
Classifier: Programming Language :: Python :: 3.8
Classifier: Programming Language :: Python :: 3.9
Classifier: Programming Language :: Python :: Implementation :: CPython
Requires-Python: >=3.7
License-File: LICENSE
